logfire/__init__.py
logfire/__main__.py
logfire/cli.py
logfire/exceptions.py
logfire/propagate.py
logfire/py.typed
logfire/query_client.py
logfire/testing.py
logfire/types.py
logfire/version.py
logfire/_internal/__init__.py
logfire/_internal/ast_utils.py
logfire/_internal/async_.py
logfire/_internal/auth.py
logfire/_internal/baggage.py
logfire/_internal/client.py
logfire/_internal/collect_system_info.py
logfire/_internal/config.py
logfire/_internal/config_params.py
logfire/_internal/constants.py
logfire/_internal/db_statement_summary.py
logfire/_internal/formatter.py
logfire/_internal/instrument.py
logfire/_internal/json_encoder.py
logfire/_internal/json_formatter.py
logfire/_internal/json_schema.py
logfire/_internal/json_types.py
logfire/_internal/logs.py
logfire/_internal/main.py
logfire/_internal/metrics.py
logfire/_internal/scrubbing.py
logfire/_internal/stack_info.py
logfire/_internal/tracer.py
logfire/_internal/ulid.py
logfire/_internal/utils.py
logfire/_internal/auto_trace/__init__.py
logfire/_internal/auto_trace/import_hook.py
logfire/_internal/auto_trace/rewrite_ast.py
logfire/_internal/auto_trace/types.py
logfire/_internal/cli/__init__.py
logfire/_internal/cli/auth.py
logfire/_internal/cli/prompt.py
logfire/_internal/cli/run.py
logfire/_internal/exporters/__init__.py
logfire/_internal/exporters/console.py
logfire/_internal/exporters/dynamic_batch.py
logfire/_internal/exporters/logs.py
logfire/_internal/exporters/otlp.py
logfire/_internal/exporters/processor_wrapper.py
logfire/_internal/exporters/quiet_metrics.py
logfire/_internal/exporters/remove_pending.py
logfire/_internal/exporters/test.py
logfire/_internal/exporters/wrapper.py
logfire/_internal/integrations/__init__.py
logfire/_internal/integrations/aiohttp_client.py
logfire/_internal/integrations/aiohttp_server.py
logfire/_internal/integrations/asgi.py
logfire/_internal/integrations/asyncpg.py
logfire/_internal/integrations/aws_lambda.py
logfire/_internal/integrations/celery.py
logfire-4.14.0.dist-info/METADATA
logfire-4.14.0.dist-info/WHEEL
logfire-4.14.0.dist-info/entry_points.txt
logfire-4.14.0.dist-info/licenses/LICENSE
logfire-4.14.0.dist-info/RECORD
