Metadata-Version: 2.4
Name: logfire
Version: 4.14.0
Summary: The best Python observability tool! 🪵🔥
Project-URL: Homepage, https://logfire.pydantic.dev/
Project-URL: Source, https://github.com/pydantic/logfire
Project-URL: Documentation, https://logfire.pydantic.dev/docs/
Project-URL: Changelog, https://logfire.pydantic.dev/docs/release-notes/
Author-email: Pydantic Team <engineering@pydantic.dev>, Samuel Colvin <samuel@pydantic.dev>, Hasan Ramezani <hasan@pydantic.dev>, Adrian Garcia Badaracco <adrian@pydantic.dev>, David Montague <david@pydantic.dev>, Marcelo Trylesinski <marcelo@pydantic.dev>, David Hewitt <david.hewitt@pydantic.dev>, Alex Hall <alex@pydantic.dev>
License-Expression: MIT
License-File: LICENSE
Classifier: Development Status :: 5 - Production/Stable
Classifier: Environment :: Console
Classifier: Environment :: MacOS X
Classifier: Framework :: OpenTelemetry
Classifier: Framework :: OpenTelemetry :: Distros
Classifier: Framework :: OpenTelemetry :: Exporters
Classifier: Framework :: OpenTelemetry :: Instrumentations
Classifier: Intended Audience :: Developers
Classifier: Intended Audience :: Information Technology
Classifier: Intended Audience :: System Administrators
Classifier: Operating System :: POSIX :: Linux
Classifier: Operating System :: Unix
Classifier: Programming Language :: Python
Classifier: Programming Language :: Python :: 3
Classifier: Programming Language :: Python :: 3 :: Only
Classifier: Programming Language :: Python :: 3.9
Classifier: Programming Language :: Python :: 3.10
Classifier: Programming Language :: Python :: 3.11
Classifier: Programming Language :: Python :: 3.12
Classifier: Programming Language :: Python :: 3.13
Classifier: Topic :: Internet
Classifier: Topic :: Software Development :: Libraries :: Python Modules
Requires-Python: >=3.9
Requires-Dist: executing>=2.0.1
Requires-Dist: opentelemetry-exporter-otlp-proto-http<1.39.0,>=1.35.0
Requires-Dist: opentelemetry-instrumentation>=0.41b0
Requires-Dist: opentelemetry-sdk<1.39.0,>=1.35.0
Requires-Dist: protobuf>=4.23.4
Requires-Dist: rich>=13.4.2
Requires-Dist: tomli>=2.0.1; python_version < '3.11'
Requires-Dist: typing-extensions>=4.1.0
Provides-Extra: aiohttp
Requires-Dist: opentelemetry-instrumentation-aiohttp-client>=0.42b0; extra == 'aiohttp'
Provides-Extra: aiohttp-client
Requires-Dist: opentelemetry-instrumentation-aiohttp-client>=0.42b0; extra == 'aiohttp-client'
Provides-Extra: aiohttp-server
Requires-Dist: opentelemetry-instrumentation-aiohttp-server>=0.55b0; extra == 'aiohttp-server'
Provides-Extra: asgi
Requires-Dist: opentelemetry-instrumentation-asgi>=0.42b0; extra == 'asgi'
Provides-Extra: asyncpg
Requires-Dist: opentelemetry-instrumentation-asyncpg>=0.42b0; extra == 'asyncpg'
Provides-Extra: aws-lambda
Requires-Dist: opentelemetry-instrumentation-aws-lambda>=0.42b0; extra == 'aws-lambda'
Provides-Extra: celery
Requires-Dist: opentelemetry-instrumentation-celery>=0.42b0; extra == 'celery'
Provides-Extra: django
Requires-Dist: opentelemetry-instrumentation-asgi>=0.42b0; extra == 'django'
Requires-Dist: opentelemetry-instrumentation-django>=0.42b0; extra == 'django'
Provides-Extra: fastapi
Requires-Dist: opentelemetry-instrumentation-fastapi>=0.42b0; extra == 'fastapi'
Provides-Extra: flask
Requires-Dist: opentelemetry-instrumentation-flask>=0.42b0; extra == 'flask'
Provides-Extra: google-genai
Requires-Dist: opentelemetry-instrumentation-google-genai>=0.4b0; extra == 'google-genai'
Provides-Extra: httpx
Requires-Dist: opentelemetry-instrumentation-httpx>=0.42b0; extra == 'httpx'
Provides-Extra: litellm
Requires-Dist: openinference-instrumentation-litellm>=0; extra == 'litellm'
Provides-Extra: mysql
Requires-Dist: opentelemetry-instrumentation-mysql>=0.42b0; extra == 'mysql'
Provides-Extra: psycopg
Requires-Dist: opentelemetry-instrumentation-psycopg>=0.42b0; extra == 'psycopg'
Requires-Dist: packaging; extra == 'psycopg'
Provides-Extra: psycopg2
Requires-Dist: opentelemetry-instrumentation-psycopg2>=0.42b0; extra == 'psycopg2'
Requires-Dist: packaging; extra == 'psycopg2'
Provides-Extra: pymongo
Requires-Dist: opentelemetry-instrumentation-pymongo>=0.42b0; extra == 'pymongo'
Provides-Extra: redis
Requires-Dist: opentelemetry-instrumentation-redis>=0.42b0; extra == 'redis'
Provides-Extra: requests
Requires-Dist: opentelemetry-instrumentation-requests>=0.42b0; extra == 'requests'
Provides-Extra: sqlalchemy
Requires-Dist: opentelemetry-instrumentation-sqlalchemy>=0.42b0; extra == 'sqlalchemy'
Provides-Extra: sqlite3
Requires-Dist: opentelemetry-instrumentation-sqlite3>=0.42b0; extra == 'sqlite3'
Provides-Extra: starlette
Requires-Dist: opentelemetry-instrumentation-starlette>=0.42b0; extra == 'starlette'
Provides-Extra: system-metrics
Requires-Dist: opentelemetry-instrumentation-system-metrics>=0.42b0; extra == 'system-metrics'
Provides-Extra: wsgi
Requires-Dist: opentelemetry-instrumentation-wsgi>=0.42b0; extra == 'wsgi'
